evoscape/__init__.py
evoscape-0.1.0.dev0.dist-info/LICENSE
evoscape-0.1.0.dev0.dist-info/METADATA
evoscape-0.1.0.dev0.dist-info/WHEEL
evoscape-0.1.0.dev0.dist-info/RECORD
