Metadata-Version: 2.1
Name: evoscape
Version: 0.1.0.dev0
Summary: 
Author: victoria-mochulska
Author-email: viktoriia.mochulska@mail.mcgill.ca
Requires-Python: >=3.11,<4.0
Classifier: Programming Language :: Python :: 3
Classifier: Programming Language :: Python :: 3.11
Classifier: Programming Language :: Python :: 3.12
Requires-Dist: cmcrameri (>=1.9,<2.0)
Requires-Dist: matplotlib (>=3.9.0,<4.0.0)
Requires-Dist: numpy (>=1.26.4,<2.0.0)
Requires-Dist: pyyaml (>=6.0.1,<7.0.0)
Requires-Dist: scikit-image (>=0.23.2,<0.24.0)
